advancedeconmodels/__init__.py
advancedeconmodels/advancedmodels.py
advancedeconmodels-1.0.1.dist-info/LICENSE
advancedeconmodels-1.0.1.dist-info/METADATA
advancedeconmodels-1.0.1.dist-info/WHEEL
advancedeconmodels-1.0.1.dist-info/top_level.txt
advancedeconmodels-1.0.1.dist-info/RECORD
