Metadata-Version: 2.1
Name: advancedeconmodels
Version: 1.0.1
Summary: This is my first module
Home-page: https://github.com/powerpom/advancedmodels/archive/master.zip
Download-URL: https://github.com/powerpom/advancedmodels/archive/master.zip
Author: pom
Author-email: 
Project-URL: Documentation, https://github.com/powerpom/advancedmodels
Classifier: Programming Language :: Python :: 3.11
Classifier: License :: OSI Approved :: MIT License
Classifier: Operating System :: OS Independent
Requires-Python: >=3.7
License-File: LICENSE
Requires-Dist: requests >=2.25.1
